setup.py
vinz_distributions/Binomialdistribution.py
vinz_distributions/Gaussiandistribution.py
vinz_distributions/Generaldistribution.py
vinz_distributions/__init__.py
vinz_distributions.egg-info/PKG-INFO
vinz_distributions.egg-info/SOURCES.txt
vinz_distributions.egg-info/dependency_links.txt
vinz_distributions.egg-info/not-zip-safe
vinz_distributions.egg-info/top_level.txt