Metadata-Version: 1.0
Name: vinz-distributions
Version: 0.1
Summary: Distributions by Vinz
Home-page: UNKNOWN
Author: Vinz
Author-email: dev@vinz.in
License: UNKNOWN
Platform: UNKNOWN
